{"Columns":[{"ShortTypeName":"int","strDateType":"int","DataType":1,"Name":"Id","DisplayName":"Id","Nullable":false,"MaxLength":0,"RangeMin":0,"RangeMax":0,"IsVisible":true,"IsNumeric":true,"HasMetaAttribute":false,"MetaAttribute":""},{"ShortTypeName":"string","strDateType":"string","DataType":0,"Name":"StudentCode","DisplayName":"StudentCode","Nullable":true,"MaxLength":10,"RangeMin":0,"RangeMax":0,"IsVisible":true,"IsNumeric":false,"HasMetaAttribute":true,"MetaAttribute":"[MaxLength(10)]"},{"ShortTypeName":"string","strDateType":"string","DataType":0,"Name":"Name","DisplayName":"Name","Nullable":true,"MaxLength":50,"RangeMin":0,"RangeMax":0,"IsVisible":true,"IsNumeric":false,"HasMetaAttribute":true,"MetaAttribute":"[MaxLength(50)]"},{"ShortTypeName":"string","strDateType":"string","DataType":0,"Name":"Family","DisplayName":"Family","Nullable":true,"MaxLength":50,"RangeMin":0,"RangeMax":0,"IsVisible":true,"IsNumeric":false,"HasMetaAttribute":true,"MetaAttribute":"[MaxLength(50)]"},{"ShortTypeName":"string","strDateType":"string","DataType":0,"Name":"Father","DisplayName":"Father","Nullable":true,"MaxLength":50,"RangeMin":0,"RangeMax":0,"IsVisible":true,"IsNumeric":false,"HasMetaAttribute":true,"MetaAttribute":"[MaxLength(50)]"},{"ShortTypeName":"string","strDateType":"string","DataType":0,"Name":"SSN","DisplayName":"SSN","Nullable":true,"MaxLength":10,"RangeMin":0,"RangeMax":0,"IsVisible":true,"IsNumeric":false,"HasMetaAttribute":true,"MetaAttribute":"[MaxLength(10)]"},{"ShortTypeName":"DateTime","strDateType":"datetime","DataType":2,"Name":"BirthDate","DisplayName":"BirthDate","Nullable":true,"MaxLength":0,"RangeMin":0,"RangeMax":0,"IsVisible":true,"IsNumeric":false,"HasMetaAttribute":false,"MetaAttribute":""},{"ShortTypeName":"DateTime","strDateType":"datetime","DataType":2,"Name":"RegDate","DisplayName":"RegDate","Nullable":true,"MaxLength":0,"RangeMin":0,"RangeMax":0,"IsVisible":true,"IsNumeric":false,"HasMetaAttribute":false,"MetaAttribute":""}]}